tmo_monitor/__init__.py
tmo_monitor/configuration.py
tmo_monitor/status.py
tmo_monitor/gateway/arcadyan.py
tmo_monitor/gateway/base.py
tmo_monitor/gateway/model.py
tmo_monitor/gateway/nokia.py
tmo_monitor-2.0.0b4.data/scripts/tmo-monitor.py
tmo_monitor-2.0.0b4.dist-info/LICENSE
tmo_monitor-2.0.0b4.dist-info/METADATA
tmo_monitor-2.0.0b4.dist-info/WHEEL
tmo_monitor-2.0.0b4.dist-info/top_level.txt
tmo_monitor-2.0.0b4.dist-info/RECORD
