Metadata-Version: 2.1
Name: tmo-monitor
Version: 2.0.0b4
Summary: A script to monitor the T-Mobile Home Internet 5G Gateways
Home-page: https://github.com/highvolt-dev/tmo-monitor
Author: highvolt-dev
License: MIT
License-File: LICENSE
Requires-Dist: parse
Requires-Dist: python-dotenv
Requires-Dist: requests
Requires-Dist: tailer
